expecter/__init__.py
expecter/plugin.py
pytest_expecter-3.0.dist-info/entry_points.txt
pytest_expecter-3.0.dist-info/LICENSE.md
pytest_expecter-3.0.dist-info/WHEEL
pytest_expecter-3.0.dist-info/METADATA
pytest_expecter-3.0.dist-info/RECORD
