Metadata-Version: 2.1
Name: pytest-expecter
Version: 3.0
Summary: Better testing with expecter and pytest.
Home-page: https://pypi.org/project/pytest-expecter
License: BSD
Keywords: pytest,testing
Author: Jace Browning
Author-email: jacebrowning@gmail.com
Requires-Python: >=3.8,<4.0
Classifier: Development Status :: 5 - Production/Stable
Classifier: Environment :: Plugins
Classifier: Framework :: Pytest
Classifier: Intended Audience :: Developers
Classifier: License :: OSI Approved :: BSD License
Classifier: License :: Other/Proprietary License
Classifier: Operating System :: OS Independent
Classifier: Programming Language :: Python
Classifier: Programming Language :: Python :: 3
Classifier: Programming Language :: Python :: 3.8
Classifier: Programming Language :: Python :: 3.9
Classifier: Programming Language :: Python :: 3.10
Classifier: Programming Language :: Python :: 3.10
Classifier: Programming Language :: Python :: 3.8
Classifier: Programming Language :: Python :: 3.9
Classifier: Topic :: Software Development :: Testing
Project-URL: Documentation, https://pytest-expecter.readthedocs.io
Project-URL: Repository, https://github.com/jacebrowning/pytest-expecter
